brunch/__init__.py
brunch/apps.py
brunch/conf.py
brunch/utils.py
brunch/management/__init__.py
brunch/management/commands/__init__.py
brunch/management/commands/runserver.py
django_brunch-1.0.4.dist-info/METADATA
django_brunch-1.0.4.dist-info/RECORD
django_brunch-1.0.4.dist-info/WHEEL
django_brunch-1.0.4.dist-info/top_level.txt
